odoo/addons/odoo_coopcycle_connector/.gitignore
odoo/addons/odoo_coopcycle_connector/__init__.py
odoo/addons/odoo_coopcycle_connector/__manifest__.py
odoo/addons/odoo_coopcycle_connector/comentaris.md
odoo/addons/odoo_coopcycle_connector/data/default_coopcycle_product.xml
odoo/addons/odoo_coopcycle_connector/data/ir_cron.xml
odoo/addons/odoo_coopcycle_connector/models/__init__.py
odoo/addons/odoo_coopcycle_connector/models/base_partner_merge.py
odoo/addons/odoo_coopcycle_connector/models/coopcycle_backend.py
odoo/addons/odoo_coopcycle_connector/models/res_config_settings.py
odoo/addons/odoo_coopcycle_connector/models/res_partner.py
odoo/addons/odoo_coopcycle_connector/models/sale_order.py
odoo/addons/odoo_coopcycle_connector/views/res_config_settings_view.xml
odoo/addons/odoo_coopcycle_connector/views/res_partner.xml
odoo/addons/odoo_coopcycle_connector/views/sale_order.xml
odoo_addon_odoo_coopcycle_connector-16.0.1.0.0.4.dist-info/METADATA
odoo_addon_odoo_coopcycle_connector-16.0.1.0.0.4.dist-info/WHEEL
odoo_addon_odoo_coopcycle_connector-16.0.1.0.0.4.dist-info/top_level.txt
odoo_addon_odoo_coopcycle_connector-16.0.1.0.0.4.dist-info/RECORD
